google_cloud_pipeline_components/__init__.py
google_cloud_pipeline_components/_image.py
google_cloud_pipeline_components/_placeholders.py
google_cloud_pipeline_components/utils.py
google_cloud_pipeline_components/version.py
google_cloud_pipeline_components/_implementation/__init__.py
google_cloud_pipeline_components/_implementation/llm/__init__.py
google_cloud_pipeline_components/_implementation/llm/batch_prediction_pairwise.py
google_cloud_pipeline_components/_implementation/llm/bulk_inferrer.py
google_cloud_pipeline_components/_implementation/llm/deploy_llm_model.py
google_cloud_pipeline_components/_implementation/llm/deployment_graph.py
google_cloud_pipeline_components/_implementation/llm/env.py
google_cloud_pipeline_components/_implementation/llm/function_based.py
google_cloud_pipeline_components/_implementation/llm/infer_preprocessor.py
google_cloud_pipeline_components/_implementation/llm/model_evaluation_text_generation_pairwise.py
google_cloud_pipeline_components/_implementation/llm/online_evaluation_pairwise.py
google_cloud_pipeline_components/_implementation/llm/preference_data_formatter.py
google_cloud_pipeline_components/_implementation/llm/preprocess_chat_dataset.py
google_cloud_pipeline_components/_implementation/llm/private_text_comparison_importer.py
google_cloud_pipeline_components/_implementation/llm/private_text_importer.py
google_cloud_pipeline_components/_implementation/llm/reinforcement_learning_graph.py
google_cloud_pipeline_components/_implementation/llm/reinforcer.py
google_cloud_pipeline_components/_implementation/llm/reward_model_graph.py
google_cloud_pipeline_components/_implementation/llm/reward_model_trainer.py
google_cloud_pipeline_components/_implementation/llm/rlhf_preprocessor.py
google_cloud_pipeline_components/_implementation/llm/supervised_fine_tuner.py
google_cloud_pipeline_components/_implementation/llm/upload_llm_model.py
google_cloud_pipeline_components/_implementation/llm/upload_tensorboard_metrics.py
google_cloud_pipeline_components-2.22.0.dist-info/LICENSE
google_cloud_pipeline_components-2.22.0.dist-info/METADATA
google_cloud_pipeline_components-2.22.0.dist-info/WHEEL
google_cloud_pipeline_components-2.22.0.dist-info/top_level.txt
google_cloud_pipeline_components-2.22.0.dist-info/RECORD
