Metadata-Version: 2.1
Name: google-cloud-pipeline-components
Version: 2.22.0
Summary: This SDK enables a set of First Party (Google owned) pipeline components that allow users to take their experience from Vertex AI SDK and other Google Cloud services and create a corresponding pipeline using KFP or Managed Pipelines.
Home-page: https://github.com/kubeflow/pipelines/tree/master/components/google-cloud
Author: The Google Cloud Pipeline Components authors
Author-email: google-cloud-pipeline-components@google.com
License: Apache License 2.0
Project-URL: User Documentation, https://cloud.google.com/vertex-ai/docs/pipelines/components-introduction
Project-URL: Reference Documentation, https://google-cloud-pipeline-components.readthedocs.io/
Project-URL: Source, https://github.com/kubeflow/pipelines/tree/master/components/google-cloud
Project-URL: Release Notes, https://github.com/kubeflow/pipelines/tree/master/components/google-cloud/RELEASE.md
Platform: UNKNOWN
Classifier: Development Status :: 4 - Beta
Classifier: Operating System :: Unix
Classifier: Operating System :: MacOS
Classifier: Intended Audience :: Developers
Classifier: Intended Audience :: Education
Classifier: Intended Audience :: Science/Research
Classifier: License :: OSI Approved :: Apache Software License
Classifier: Programming Language :: Python :: 3
Classifier: Programming Language :: Python :: 3.8
Classifier: Programming Language :: Python :: 3.9
Classifier: Programming Language :: Python :: 3.10
Classifier: Programming Language :: Python :: 3.11
Classifier: Programming Language :: Python :: 3.12
Classifier: Programming Language :: Python :: 3.13
Classifier: Topic :: Scientific/Engineering
Classifier: Topic :: Scientific/Engineering :: Artificial Intelligence
Classifier: Topic :: Software Development
Classifier: Topic :: Software Development :: Libraries
Classifier: Topic :: Software Development :: Libraries :: Python Modules
Requires-Python: >=3.8.0
License-File: LICENSE
Requires-Dist: google-api-core (!=2.0.*,!=2.1.*,!=2.2.*,!=2.3.0,<3.0.0dev,>=1.31.5)
Requires-Dist: kfp (<3.0.0,>=2.6.0)
Requires-Dist: google-cloud-aiplatform (<2,>=1.14.0)
Requires-Dist: Jinja2 (<4,>=3.1.2)
Provides-Extra: docs
Requires-Dist: protobuf (<5,>=4.21.1) ; extra == 'docs'
Requires-Dist: grpcio-status (<=1.47.0) ; extra == 'docs'
Requires-Dist: commonmark (==0.9.1) ; extra == 'docs'
Requires-Dist: autodocsumm (==0.2.9) ; extra == 'docs'
Requires-Dist: sphinx (<6.0.0,>=5.0.2) ; extra == 'docs'
Requires-Dist: sphinx-immaterial (==0.9.0) ; extra == 'docs'
Requires-Dist: sphinx-rtd-theme (==2.0.0) ; extra == 'docs'
Requires-Dist: m2r2 (==0.3.3.post2) ; extra == 'docs'
Requires-Dist: sphinx-notfound-page (==0.8.3) ; extra == 'docs'
Provides-Extra: tests
Requires-Dist: mock (>=4.0.0) ; extra == 'tests'
Requires-Dist: flake8 (>=3.0.0) ; extra == 'tests'
Requires-Dist: pytest (>=6.0.0) ; extra == 'tests'
